MANIFEST.in
README.rst
setup.py
docs/HISTORY.txt
docs/LICENSE.GPL
docs/LICENSE.txt
ftw/__init__.py
ftw.iframefix.egg-info/PKG-INFO
ftw.iframefix.egg-info/SOURCES.txt
ftw.iframefix.egg-info/dependency_links.txt
ftw.iframefix.egg-info/entry_points.txt
ftw.iframefix.egg-info/namespace_packages.txt
ftw.iframefix.egg-info/not-zip-safe
ftw.iframefix.egg-info/requires.txt
ftw.iframefix.egg-info/top_level.txt
ftw/iframefix/__init__.py
ftw/iframefix/configure.zcml
ftw/iframefix/testing.py
ftw/iframefix/Extensions/__init__.py
ftw/iframefix/Extensions/install.py
ftw/iframefix/profiles/default/metadata.xml
ftw/iframefix/profiles/uninstall/.gitkeep
ftw/iframefix/resources/resources.zcml
ftw/iframefix/resources/scss/iefixes.scss
ftw/iframefix/resources/scss/webkitfixes.scss
ftw/iframefix/tests/__init__.py
ftw/iframefix/tests/test_profiles.py
ftw/iframefix/tests/test_uninstall.py
ftw/iframefix/upgrades/__init__.py